.dir-locals.el
.hgignore
.hgtags
HISTORY.rst
README.rst
TODO.txt
mercurial_path_pattern.py
noxfile.py
setup.py
mercurial_path_pattern.egg-info/PKG-INFO
mercurial_path_pattern.egg-info/SOURCES.txt
mercurial_path_pattern.egg-info/dependency_links.txt
mercurial_path_pattern.egg-info/requires.txt
mercurial_path_pattern.egg-info/top_level.txt
mercurial_path_pattern.egg-info/zip-safe
tests/basic.t
tests/name-reuse-compact.t
tests/name-reuse-long.t