Metadata-Version: 2.1
Name: mercurial_path_pattern
Version: 1.4.3
Summary: Mercurial Path Pattern Extension
Home-page: https://foss.heptapod.net/mercurial/mercurial-path_pattern
Author: Marcin Kasperski
Author-email: Marcin.Kasperski@mekk.waw.pl
License: BSD
Keywords: mercurial hg path alias
Classifier: Development Status :: 5 - Production/Stable
Classifier: Environment :: Console
Classifier: Intended Audience :: Developers
Classifier: License :: DFSG approved
Classifier: License :: OSI Approved :: BSD License
Classifier: Programming Language :: Python :: 2
Classifier: Programming Language :: Python :: 3
Classifier: Operating System :: OS Independent
Classifier: Topic :: Software Development :: Version Control
Requires-Dist: mercurial_extension_utils>=1.5.0
